Metadata-Version: 2.4
Name: afnio
Version: 0.3.2
Summary: Afnio Python library and Tellurio Studio CLI tool
Author-email: Tellurio <contact@tellurio.ai>
License:                     GNU AFFERO GENERAL PUBLIC LICENSE
Project-URL: homepage, https://github.com/Tellurio-AI/afnio
Project-URL: repository, https://github.com/Tellurio-AI/afnio
Keywords: ai-agent,language-models,prompt-optimization,afnio
Classifier: Programming Language :: Python :: 3.9
Classifier: Programming Language :: Python :: 3.10
Classifier: Programming Language :: Python :: 3.11
Classifier: Programming Language :: Python :: 3.12
Classifier: License :: OSI Approved :: GNU Affero General Public License v3
Requires-Python: >=3.9
License-File: LICENSE.md
Requires-Dist: click<9,>=8.1.8
Requires-Dist: httpx<1,>=0.28.1
Requires-Dist: ipython<10,>=7.34.0
Requires-Dist: ipywidgets<9,>=8.1.7
Requires-Dist: keyring<26,>=25.6.0
Requires-Dist: openai<2,>=1.106.1
Requires-Dist: python-dotenv<2,>=1.1.0
Requires-Dist: python-slugify<9,>=8.0.4
Requires-Dist: rich<15,>=13.9.4
Requires-Dist: websockets<16,>=15.0.1
Provides-Extra: testing
Requires-Dist: pytest>=8.3.5; extra == "testing"
Requires-Dist: pytest-asyncio>=0.26.0; extra == "testing"
Dynamic: license-file
